ddmtolab/__init__.py
ddmtolab/Algorithms/__init__.py
ddmtolab/Algorithms/MTMO/EMTET.py
ddmtolab/Algorithms/MTMO/EMTPD.py
ddmtolab/Algorithms/MTMO/MOEMEA.py
ddmtolab/Algorithms/MTMO/MOMFEA.py
ddmtolab/Algorithms/MTMO/MOMFEAII.py
ddmtolab/Algorithms/MTMO/MOMTEASaO.py
ddmtolab/Algorithms/MTMO/MTDEMKTA.py
ddmtolab/Algorithms/MTMO/MTEADDN.py
ddmtolab/Algorithms/MTMO/ParEGONT.py
ddmtolab/Algorithms/MTMO/__init__.py
ddmtolab/Algorithms/MTSO/BO_LCB_BCKT.py
ddmtolab/Algorithms/MTSO/BO_LCB_CKT.py
ddmtolab/Algorithms/MTSO/EBS.py
ddmtolab/Algorithms/MTSO/EEIBOplus.py
ddmtolab/Algorithms/MTSO/EMEA.py
ddmtolab/Algorithms/MTSO/GMFEA.py
ddmtolab/Algorithms/MTSO/LCBEMT.py
ddmtolab/Algorithms/MTSO/MFEA.py
ddmtolab/Algorithms/MTSO/MFEAII.py
ddmtolab/Algorithms/MTSO/MKTDE.py
ddmtolab/Algorithms/MTSO/MTBO.py
ddmtolab/Algorithms/MTSO/MTEAAD.py
ddmtolab/Algorithms/MTSO/MTEASaO.py
ddmtolab/Algorithms/MTSO/MUMBO.py
ddmtolab/Algorithms/MTSO/RAMTEA.py
ddmtolab/Algorithms/MTSO/SELF.py
ddmtolab/Algorithms/MTSO/SREMTO.py
ddmtolab/Algorithms/MTSO/__init__.py
ddmtolab/Algorithms/STMO/CCMO.py
ddmtolab/Algorithms/STMO/CPSMOEA.py
ddmtolab/Algorithms/STMO/CTAEA.py
ddmtolab/Algorithms/STMO/DSAEAPS.py
ddmtolab/Algorithms/STMO/IBEA.py
ddmtolab/Algorithms/STMO/KRVEA.py
ddmtolab/Algorithms/STMO/KTA2.py
ddmtolab/Algorithms/STMO/MCEAD.py
ddmtolab/Algorithms/STMO/MOEAD.py
ddmtolab/Algorithms/STMO/MOEADD.py
ddmtolab/Algorithms/STMO/MOEADFRRMAB.py
ddmtolab/Algorithms/STMO/MOEADSTM.py
ddmtolab/Algorithms/STMO/MSEA.py
ddmtolab/Algorithms/STMO/NSGAII.py
ddmtolab/Algorithms/STMO/NSGAIII.py
ddmtolab/Algorithms/STMO/NSGAIISDR.py
ddmtolab/Algorithms/STMO/ParEGO.py
ddmtolab/Algorithms/STMO/REMO.py
ddmtolab/Algorithms/STMO/RVEA.py
ddmtolab/Algorithms/STMO/SPEA2.py
ddmtolab/Algorithms/STMO/TwoArch2.py
ddmtolab/Algorithms/STMO/__init__.py
ddmtolab/Algorithms/STSO/AO.py
ddmtolab/Algorithms/STSO/BO.py
ddmtolab/Algorithms/STSO/CMAES.py
ddmtolab/Algorithms/STSO/CSO.py
ddmtolab/Algorithms/STSO/DE.py
ddmtolab-1.0.0.dist-info/licenses/LICENSE
ddmtolab-1.0.0.dist-info/METADATA
ddmtolab-1.0.0.dist-info/WHEEL
ddmtolab-1.0.0.dist-info/top_level.txt
ddmtolab-1.0.0.dist-info/RECORD
