Metadata-Version: 2.4
Name: ddmtolab
Version: 1.0.0
Summary: Data-Driven Multitask Optimization Laboratory
Author-email: Jiangtao Shen <j.shen5@exeter.ac.uk>
License: MIT
Project-URL: Homepage, https://github.com/JiangtaoShen/DDMTOLab
Project-URL: Documentation, https://jiangtaoshen.github.io/DDMTOLab/
Project-URL: Bug Tracker, https://github.com/JiangtaoShen/DDMTOLab/issues
Keywords: optimization,multitask-optimization,evolutionary-algorithm,surrogate-model,bayesian-optimization,machine-learning
Classifier: Development Status :: 4 - Beta
Classifier: Intended Audience :: Science/Research
Classifier: Intended Audience :: Developers
Classifier: License :: OSI Approved :: MIT License
Classifier: Programming Language :: Python :: 3
Classifier: Programming Language :: Python :: 3.10
Classifier: Programming Language :: Python :: 3.11
Classifier: Programming Language :: Python :: 3.12
Classifier: Topic :: Scientific/Engineering :: Artificial Intelligence
Classifier: Topic :: Scientific/Engineering :: Mathematics
Requires-Python: >=3.10
License-File: LICENSE
Requires-Dist: numpy>=2.0.1
Requires-Dist: scipy>=1.15.3
Requires-Dist: pandas>=2.3.3
Requires-Dist: matplotlib>=3.10.6
Requires-Dist: scikit-learn>=1.7.2
Requires-Dist: tqdm>=4.67.1
Requires-Dist: openpyxl>=3.1.5
Requires-Dist: seaborn>=0.13.2
Requires-Dist: pyyaml>=6.0.2
Requires-Dist: bottleneck>=1.4.2
Requires-Dist: torch>=2.5.1
Requires-Dist: botorch>=0.16.0
Requires-Dist: gpytorch>=1.14.2
Requires-Dist: pyro-ppl>=1.9.1
Provides-Extra: dev
Requires-Dist: pytest>=7.0; extra == "dev"
Requires-Dist: pytest-cov; extra == "dev"
Requires-Dist: black; extra == "dev"
Requires-Dist: flake8; extra == "dev"
Requires-Dist: sphinx>=7.4.7; extra == "dev"
Requires-Dist: sphinx-rtd-theme>=3.0.2; extra == "dev"
Requires-Dist: sphinx-autodoc-typehints>=2.3.0; extra == "dev"
Requires-Dist: myst-parser>=3.0.1; extra == "dev"
Provides-Extra: all
Requires-Dist: ddmtolab[dev]; extra == "all"
Dynamic: license-file
